setup.py
insight_gateway_python_v4.0.4.egg-info/PKG-INFO
insight_gateway_python_v4.0.4.egg-info/SOURCES.txt
insight_gateway_python_v4.0.4.egg-info/dependency_links.txt
insight_gateway_python_v4.0.4.egg-info/requires.txt
insight_gateway_python_v4.0.4.egg-info/top_level.txt
insight_gateway_python_v400/com/data_handle.py
insight_gateway_python_v400/com/functional_test.py
insight_gateway_python_v400/com/log_handle.py
insight_gateway_python_v400/com/interface/mdc_gateway_base_define.py
insight_gateway_python_v400/com/interface/mdc_gateway_head.py
insight_gateway_python_v400/com/interface/mdc_gateway_interface.py
insight_gateway_python_v400/com/interface/mdc_query_client.py
insight_gateway_python_v400/com/interface/mdc_query_client_factory.py
insight_gateway_python_v400/com/interface/mdc_recvdata_interface.py
insight_gateway_python_v400/com/libs/python37/x64/mdc_gateway_client.py
insight_gateway_python_v400/com/data_handle.py
insight_gateway_python_v400/com/functional_test.py
insight_gateway_python_v400/com/log_handle.py
insight_gateway_python_v400/com/cert/HTISCA.crt
insight_gateway_python_v400/com/cert/HTInsightCA.crt
insight_gateway_python_v400/com/cert/InsightClientCert.pem
insight_gateway_python_v400/com/interface/mdc_gateway_base_define.py
insight_gateway_python_v400/com/interface/mdc_gateway_head.py
insight_gateway_python_v400/com/interface/mdc_gateway_interface.py
insight_gateway_python_v400/com/interface/mdc_query_client.py
insight_gateway_python_v400/com/interface/mdc_query_client_factory.py
insight_gateway_python_v400/com/interface/mdc_recvdata_interface.py
insight_gateway_python_v400/com/libs/python37/x64/ACE.dll
insight_gateway_python_v400/com/libs/python37/x64/ACE_SSL.dll
insight_gateway_python_v400/com/libs/python37/x64/_mdc_gateway_client.pyd
insight_gateway_python_v400/com/libs/python37/x64/libeay32.dll
insight_gateway_python_v400/com/libs/python37/x64/mdc_gateway_client.py
insight_gateway_python_v400/com/libs/python37/x64/ssleay32.dll