Metadata-Version: 2.1
Name: insight_gateway_python_v4.0.4
Version: 4.0.4
Summary: insight_gateway_python_4.0.4
Home-page: UNKNOWN
Author: htsc
Author-email: insight@htsc.com
License: insightpythonsdk
Project-URL: Documentation, https://packaging.python.org/tutorials/distributing-packages/
Project-URL: Funding, https://donate.pypi.org
Project-URL: Source, https://github.com/pypa/sampleproject/
Project-URL: Tracker, https://github.com/pypa/sampleproject/issues
Platform: UNKNOWN
Requires-Python: >=3.7
